{
    "branding" : {
        "background" : "https://images.unsplash.com/photo-1616763355603-9755a640a287?ixlib=rb-1.2.1&ixid=MnwxMjA3fDB8MHxwaG90by1wYWdlfHx8fGVufDB8fHx8&auto=format&fit=crop&w=1470&q=80",
        "logo": {
            "light": "demo/assets/images/logo-dark.svg",
            "dark": "demo/assets/images/logo-light.svg"
        },
        "main": {
            "title": "Logo Title",
            "subtitle": "subtitle"
        },
        "footer" : {
            "title" : "Supported by",
            "subtitle": "subbie"
        }
    },
    "content" : {
        "copyright" : {
            "statement" : "Copyright 2022",
            "terms" : "Terms and conditions"
        }
    }
}
